murph/__init__.py
murph/message/__init__.py
murph/message/base.py
murph/message/base_meta.py
murph/message/fields.py
murph/service/__init__.py
murph/service/base.py
murph/service/base_meta.py
murph/service/service_method.py
murph-0.0.1.dist-info/LICENSE
murph-0.0.1.dist-info/METADATA
murph-0.0.1.dist-info/WHEEL
murph-0.0.1.dist-info/top_level.txt
murph-0.0.1.dist-info/RECORD
