Metadata-Version: 2.1
Name: murph
Version: 0.0.1
Summary: Murph is a fast and efficient Python framework for building GRPC services. With automatic Protobuf file generation and a simplified development process, Murph makes it easy to build high-performance services with ease.
Home-page: https://github.com/mgesoftware/murph
Author: Alexandru Plesoiu
Author-email: alexandru@mgesoftware.com
License: BSD 3-Clause "New" or "Revised"
Project-URL: Documentation, https://murph.readthedocs.io
Project-URL: Source Code, https://github.com/mgesoftware/murph
Project-URL: Issue Tracker, https://github.com/mgesoftware/murph/issues
Project-URL: PyPI, https://pypi.org/project/murph/
Keywords: grpc,grpc-services,grpc-framework,python-framework,protobufs,django-like-models,async,high-performance,efficient,network-programming,web-development,real-time-applications,mge,mgesoftware,murph,murph-framework,framework,django,flask,grpcio
Classifier: Development Status :: 3 - Alpha
Classifier: Intended Audience :: Developers
Classifier: Topic :: Software Development :: Libraries
Classifier: Programming Language :: Python :: 3
Classifier: Programming Language :: Python :: 3.10
Classifier: Programming Language :: Python :: 3.11
Classifier: Operating System :: OS Independent
Classifier: Topic :: System :: Networking
Classifier: Topic :: Internet
Classifier: License :: OSI Approved :: BSD License
Classifier: Framework :: AsyncIO
Classifier: Framework :: Django
Classifier: Framework :: Flask
Classifier: Typing :: Typed
Requires-Python: >=3.8
License-File: LICENSE
Requires-Dist: grpcio-tools (>=1.51.3)
